veq/__init__.py
veq/__main__.py
veq/calculator.py
veq/tokens.py
veq/visualizer.py
veq-1.3.9.dist-info/LICENSE
veq-1.3.9.dist-info/METADATA
veq-1.3.9.dist-info/WHEEL
veq-1.3.9.dist-info/entry_points.txt
veq-1.3.9.dist-info/top_level.txt
veq-1.3.9.dist-info/RECORD
