Metadata-Version: 2.1
Name: veq
Version: 1.3.9
Summary: Equation visualizer.
Home-page: https://github.com/wciesialka/riemann-sum-py
Author: Willow Ciesialka
Author-email: wciesialka@gmail.com
License: GPL-3.0
Keywords: python image math
Platform: UNKNOWN
Classifier: License :: OSI Approved :: GNU General Public License v3 or later (GPLv3+)
Classifier: Programming Language :: Python :: 3
Classifier: Topic :: Artistic Software
Classifier: Operating System :: OS Independent
Classifier: Topic :: Scientific/Engineering :: Mathematics
Requires-Python: >=3.8.10
License-File: LICENSE
Requires-Dist: pygame (==2.1.2)
